pygame_orion/__init__.py
pygame_orion/_constants.py
pygame_orion/_events.py
pygame_orion/_logging.py
pygame_orion/_prepare.py
pygame_orion/core/__init__.py
pygame_orion/core/config.py
pygame_orion/core/display.py
pygame_orion/core/emitter.py
pygame_orion/core/game.py
pygame_orion/data/__init__.py
pygame_orion/ecs/__init__.py
pygame_orion/ecs/ecs_manager.py
pygame_orion/gui/__init__.py
pygame_orion/input/__init__.py
pygame_orion/input/input_manager.py
pygame_orion/renderer/__init__.py
pygame_orion/renderer/renderer.py
pygame_orion/scenes/__init__.py
pygame_orion/scenes/constants.py
pygame_orion/scenes/scene.py
pygame_orion/scenes/scene_manager.py
pygame_orion-0.1.0.dist-info/LICENSE.txt
pygame_orion-0.1.0.dist-info/WHEEL
pygame_orion-0.1.0.dist-info/METADATA
pygame_orion-0.1.0.dist-info/RECORD
